randgraph/__init__.py
randgraph/randgraph.py
randgraph-0.1.2.dist-info/METADATA
randgraph-0.1.2.dist-info/WHEEL
randgraph-0.1.2.dist-info/top_level.txt
randgraph-0.1.2.dist-info/RECORD
