Metadata-Version: 2.1
Name: randgraph
Version: 0.1.2
Summary: A package for generating and drawing randomly generated graphs
Home-page: https://github.com/DomNidy/randgraph
Author: Dominic Nidy
Author-email: domnidy01@gmail.com
Requires-Dist: matplotlib
Requires-Dist: networkx
